{
  "xsd": "https:\/\/ibm.com\/daas\/module\/1.0\/module.xsd",
  "source": {
    "id": "StringID",
    "srcUrl": {
      "sourceUrl": "https:\/\/raw.githubusercontent.com\/Sunivihaan\/sampleapp\/master\/static\/json\/UNdata_Export.csv",
      "mimeType": "text\/csv",
      "property": [
        {
          "name": "separator",
          "value": ", "
        },
        {
          "name": "ColumnNamesLine",
          "value": "true"
        }
      ]
    }
  },
  "table": {
    "name": "Undata Exports",
    "description": "description of the table for visual hints ",
    "column": [
      {
        "name": "Country",
        "description": "Country",
        "datatype": "NVARCHAR(100)",
        "nullable": true,
        "label": "Country",
        "usage": "attribute",
        "regularAggregate": "none",
	"taxonomyFamily": "cCountry"
      }
    ]
  },
  "label": "Module Name",
  "identifier": "moduleId"
}
